session_lambda/__init__.py
session_lambda/session.py
session_lambda/store/__init__.py
session_lambda/store/base.py
session_lambda/store/dynamodb_store.py
session_lambda/store/json_file_store.py
session_lambda/store/runtime_store.py
session_lambda-0.3.6.dist-info/WHEEL
session_lambda-0.3.6.dist-info/METADATA
session_lambda-0.3.6.dist-info/RECORD
