Metadata-Version: 2.1
Name: session-lambda
Version: 0.3.6
Summary: A simple session manager for aws lambda function using dynamodb
Home-page: https://github.com/roy-pstr/session-lambda
License: MIT
Keywords: aws lambda,session,dynamodb
Author: Roy Pasternak
Author-email: roy.pasternakk@gmail.com
Requires-Python: >=3.7,<4.0
Classifier: License :: OSI Approved :: MIT License
Classifier: Programming Language :: Python :: 3
Classifier: Programming Language :: Python :: 3.7
Classifier: Programming Language :: Python :: 3.8
Classifier: Programming Language :: Python :: 3.9
Classifier: Programming Language :: Python :: 3.10
Classifier: Programming Language :: Python :: 3.11
Requires-Dist: boto3 (>=1.26.60,<2.0.0)
Project-URL: Repository, https://github.com/roy-pstr/session-lambda
